{
  "sentences": [
    {
      "id": 1,
      "text": "Épisode 1 Piste 7 Page 20",
      "translations": {
        "zh": "第一集 第七轨 第二十页",
        "en": "Episode 1 Track 7 Page 20",
        "es": "Episodio 1 Pista 7 Página 20"
      },
      "start": 0.56,
      "end": 7.2,
      "words": [
        {
          "text": "Épisode",
          "start": 0.56,
          "end": 1.28
        },
        {
          "text": "1",
          "start": 1.44,
          "end": 1.6
        },
        {
          "text": "Piste",
          "start": 2.88,
          "end": 3.28
        },
        {
          "text": "7",
          "start": 4.08,
          "end": 4.24
        },
        {
          "text": "Page",
          "start": 4.24,
          "end": 4.48
        },
        {
          "text": "20",
          "start": 6.16,
          "end": 7.2
        }
      ],
      "chunks": [
        {
          "text": "Épisode 1",
          "translations": {
            "zh": "第一集",
            "en": "Episode 1",
            "es": "Episodio 1"
          },
          "start": 0.56,
          "end": 1.6
        },
        {
          "text": "Piste 7",
          "translations": {
            "zh": "第七轨",
            "en": "Track 7",
            "es": "Pista 7"
          },
          "start": 2.88,
          "end": 4.24
        },
        {
          "text": "Page 20",
          "translations": {
            "zh": "第二十页",
            "en": "Page 20",
            "es": "Página 20"
          },
          "start": 4.24,
          "end": 7.2
        }
      ]
    },
    {
      "id": 2,
      "text": "Marie-France : Quand j'étais jeune, j'habitais au Manitoba.",
      "translations": {
        "zh": "Marie-France：我年轻的时候，住在曼尼托巴。",
        "en": "Marie-France: When I was young, I lived in Manitoba.",
        "es": "Marie-France : Cuando era joven, vivía en Manitoba."
      },
      "start": 9.04,
      "end": 12.64,
      "words": [
        {
          "text": "Marie",
          "start": 9.04,
          "end": 9.04
        },
        {
          "text": "France",
          "start": 10.0,
          "end": 10.0
        },
        {
          "text": "Quand",
          "start": 10.0,
          "end": 10.16
        },
        {
          "text": "j'étais",
          "start": 10.16,
          "end": 10.48
        },
        {
          "text": "jeune",
          "start": 10.48,
          "end": 10.72
        },
        {
          "text": "j'habitais",
          "start": 11.2,
          "end": 11.76
        },
        {
          "text": "au",
          "start": 11.76,
          "end": 11.84
        },
        {
          "text": "Manitoba",
          "start": 11.84,
          "end": 12.64
        }
      ],
      "chunks": [
        {
          "text": "Marie-France :",
          "translations": {
            "zh": "Marie-France：",
            "en": "Marie-France:",
            "es": "Marie-France :"
          },
          "start": 9.04,
          "end": 10.0
        },
        {
          "text": "Quand j'étais jeune,",
          "translations": {
            "zh": "我年轻的时候，",
            "en": "When I was young,",
            "es": "Cuando era joven,"
          },
          "start": 10.0,
          "end": 10.72
        },
        {
          "text": "j'habitais au Manitoba.",
          "translations": {
            "zh": "我住在曼尼托巴。",
            "en": "I lived in Manitoba.",
            "es": "vivía en Manitoba."
          },
          "start": 11.2,
          "end": 12.64
        }
      ]
    },
    {
      "id": 3,
      "text": "Geneviève : Hier, il faisait froid et il ventait beaucoup.",
      "translations": {
        "zh": "Geneviève：昨天，天很冷，而且风很大。",
        "en": "Geneviève: Yesterday, it was cold and it was very windy.",
        "es": "Geneviève : Ayer, hacía frío y soplaba mucho viento."
      },
      "start": 14.08,
      "end": 17.6,
      "words": [
        {
          "text": "Geneviève",
          "start": 14.08,
          "end": 15.84
        },
        {
          "text": "Hier",
          "start": 15.84,
          "end": 15.84
        },
        {
          "text": "il",
          "start": 16.0,
          "end": 16.0
        },
        {
          "text": "faisait",
          "start": 16.08,
          "end": 16.32
        },
        {
          "text": "froid",
          "start": 16.32,
          "end": 16.72
        },
        {
          "text": "et",
          "start": 16.72,
          "end": 16.8
        },
        {
          "text": "il",
          "start": 16.8,
          "end": 16.96
        },
        {
          "text": "ventait",
          "start": 16.96,
          "end": 17.2
        },
        {
          "text": "beaucoup",
          "start": 17.2,
          "end": 17.6
        }
      ],
      "chunks": [
        {
          "text": "Geneviève :",
          "translations": {
            "zh": "Geneviève：",
            "en": "Geneviève:",
            "es": "Geneviève :"
          },
          "start": 14.08,
          "end": 15.84
        },
        {
          "text": "Hier,",
          "translations": {
            "zh": "昨天，",
            "en": "Yesterday,",
            "es": "Ayer,"
          },
          "start": 15.84,
          "end": 15.84
        },
        {
          "text": "il faisait froid",
          "translations": {
            "zh": "天很冷",
            "en": "it was cold",
            "es": "hacía frío"
          },
          "start": 16.0,
          "end": 16.72
        },
        {
          "text": "et il ventait beaucoup.",
          "translations": {
            "zh": "而且风很大。",
            "en": "and it was very windy.",
            "es": "y soplaba mucho viento."
          },
          "start": 16.72,
          "end": 17.6
        }
      ]
    },
    {
      "id": 4,
      "text": "Thomas : L'année passée, je travaillais dans un café.",
      "translations": {
        "zh": "Thomas：去年，我在一家咖啡馆工作。",
        "en": "Thomas: Last year, I was working in a café.",
        "es": "Thomas : El año pasado, trabajaba en un café."
      },
      "start": 19.44,
      "end": 22.96,
      "words": [
        {
          "text": "Thomas",
          "start": 19.44,
          "end": 19.76
        },
        {
          "text": "L'année",
          "start": 21.2,
          "end": 21.44
        },
        {
          "text": "passée",
          "start": 21.44,
          "end": 21.84
        },
        {
          "text": "je",
          "start": 21.84,
          "end": 21.92
        },
        {
          "text": "travaillais",
          "start": 21.92,
          "end": 22.32
        },
        {
          "text": "dans",
          "start": 22.32,
          "end": 22.48
        },
        {
          "text": "un",
          "start": 22.48,
          "end": 22.56
        },
        {
          "text": "café",
          "start": 22.56,
          "end": 22.96
        }
      ],
      "chunks": [
        {
          "text": "Thomas :",
          "translations": {
            "zh": "Thomas：",
            "en": "Thomas:",
            "es": "Thomas :"
          },
          "start": 19.44,
          "end": 19.76
        },
        {
          "text": "L'année passée,",
          "translations": {
            "zh": "去年，",
            "en": "Last year,",
            "es": "El año pasado,"
          },
          "start": 21.2,
          "end": 21.84
        },
        {
          "text": "je travaillais dans un café.",
          "translations": {
            "zh": "我在一家咖啡馆工作。",
            "en": "I was working in a café.",
            "es": "trabajaba en un café."
          },
          "start": 21.84,
          "end": 22.96
        }
      ]
    },
    {
      "id": 5,
      "text": "Marie-France : Quand j'étais petite, j'étais très timide.",
      "translations": {
        "zh": "Marie-France：我小的时候，很害羞。",
        "en": "Marie-France: When I was little, I was very shy.",
        "es": "Marie-France : Cuando era pequeña, era muy tímida."
      },
      "start": 25.36,
      "end": 28.64,
      "words": [
        {
          "text": "Marie",
          "start": 25.36,
          "end": 25.52
        },
        {
          "text": "France",
          "start": 26.48,
          "end": 26.48
        },
        {
          "text": "Quand",
          "start": 26.48,
          "end": 26.64
        },
        {
          "text": "j'étais",
          "start": 26.64,
          "end": 26.88
        },
        {
          "text": "petite",
          "start": 26.88,
          "end": 27.36
        },
        {
          "text": "j'étais",
          "start": 27.68,
          "end": 28.0
        },
        {
          "text": "très",
          "start": 28.0,
          "end": 28.16
        },
        {
          "text": "timide",
          "start": 28.24,
          "end": 28.64
        }
      ],
      "chunks": [
        {
          "text": "Marie-France :",
          "translations": {
            "zh": "Marie-France：",
            "en": "Marie-France:",
            "es": "Marie-France :"
          },
          "start": 25.36,
          "end": 26.48
        },
        {
          "text": "Quand j'étais petite,",
          "translations": {
            "zh": "我小的时候，",
            "en": "When I was little,",
            "es": "Cuando era pequeña,"
          },
          "start": 26.48,
          "end": 27.36
        },
        {
          "text": "j'étais très timide.",
          "translations": {
            "zh": "我很害羞。",
            "en": "I was very shy.",
            "es": "era muy tímida."
          },
          "start": 27.68,
          "end": 28.64
        }
      ]
    },
    {
      "id": 6,
      "text": "Geneviève : Avant, j'allais au gym trois fois par semaine.",
      "translations": {
        "zh": "Geneviève：以前，我每周去健身房三次。",
        "en": "Geneviève: Before, I used to go to the gym three times a week.",
        "es": "Geneviève : Antes, iba al gimnasio tres veces por semana."
      },
      "start": 31.04,
      "end": 34.72,
      "words": [
        {
          "text": "Geneviève",
          "start": 31.04,
          "end": 31.44
        },
        {
          "text": "Avant",
          "start": 32.48,
          "end": 32.96
        },
        {
          "text": "j'allais",
          "start": 33.04,
          "end": 33.36
        },
        {
          "text": "au",
          "start": 33.36,
          "end": 33.44
        },
        {
          "text": "gym",
          "start": 33.44,
          "end": 33.76
        },
        {
          "text": "trois",
          "start": 33.76,
          "end": 33.92
        },
        {
          "text": "fois",
          "start": 33.92,
          "end": 34.08
        },
        {
          "text": "par",
          "start": 34.08,
          "end": 34.24
        },
        {
          "text": "semaine",
          "start": 34.24,
          "end": 34.72
        }
      ],
      "chunks": [
        {
          "text": "Geneviève :",
          "translations": {
            "zh": "Geneviève：",
            "en": "Geneviève:",
            "es": "Geneviève :"
          },
          "start": 31.04,
          "end": 31.44
        },
        {
          "text": "Avant,",
          "translations": {
            "zh": "以前，",
            "en": "Before,",
            "es": "Antes,"
          },
          "start": 32.48,
          "end": 32.96
        },
        {
          "text": "j'allais au gym",
          "translations": {
            "zh": "我去健身房",
            "en": "I used to go to the gym",
            "es": "iba al gimnasio"
          },
          "start": 33.04,
          "end": 33.76
        },
        {
          "text": "trois fois par semaine.",
          "translations": {
            "zh": "每周三次。",
            "en": "three times a week.",
            "es": "tres veces por semana."
          },
          "start": 33.76,
          "end": 34.72
        }
      ]
    }
  ],
  "id": "FLS2_EP01_P7",
  "audio_filename": "FLS2_EP01_P7.mp3",
  "audio_path": "downloads/FLS2_EP01_P7.mp3",
  "episode": 1,
  "piste": 7,
  "page": 20,
  "cd": "CD1"
}
